{
"type": "FeatureCollection",
"name": "Zone 1",
"features": [
{ "type": "Feature", "properties": { "Name": "Point 1" }, "geometry": { "type": "Point", "coordinates": [ -87.7755994, 41.9091938, 0.0 ] } },
{ "type": "Feature", "properties": { "Name": "Point 2" }, "geometry": { "type": "Point", "coordinates": [ -87.7834108, 41.9091412, 0.0 ] } },
{ "type": "Feature", "properties": { "Name": "Point 3" }, "geometry": { "type": "Point", "coordinates": [ -87.7849129, 41.8945599, 0.0 ] } },
{ "type": "Feature", "properties": { "Name": "Point 4" }, "geometry": { "type": "Point", "coordinates": [ -87.7751496, 41.8946877, 0.0 ] } }
]
}
