{
"type": "FeatureCollection",
"name": "Zone 1",
"features": [
{ "type": "Feature", "properties": { "Name": "Point 1" }, "geometry": { "type": "Point", "coordinates": [ -87.7755994, 41.9091938, 0.0 ] } },
{ "type": "Feature", "properties": { "Name": "Point 2" }, "geometry": { "type": "Point", "coordinates": [ -87.7834108, 41.9091412, 0.0 ] } },
{ "type": "Feature", "properties": { "Name": "Point 2.1" }, "geometry": { "type": "Point", "coordinates": [ -87.7832978, 41.9059154, 0.0 ] } },
{ "type": "Feature", "properties": { "Name": "Point 2.2" }, "geometry": { "type": "Point", "coordinates": [ -87.7841561, 41.9038393, 0.0 ] } },
{ "type": "Feature", "properties": { "Name": "Point 2.3" }, "geometry": { "type": "Point", "coordinates": [ -87.7841945, 41.9019481, 0.0 ] } },
{ "type": "Feature", "properties": { "Name": "Point 2.4" }, "geometry": { "type": "Point", "coordinates": [ -87.7848646, 41.9018682, 0.0 ] } },
{ "type": "Feature", "properties": { "Name": "Point 2.5" }, "geometry": { "type": "Point", "coordinates": [ -87.7851221, 41.9012613, 0.0 ] } },
{ "type": "Feature", "properties": { "Name": "Point 3" }, "geometry": { "type": "Point", "coordinates": [ -87.7849129, 41.8945599, 0.0 ] } },
{ "type": "Feature", "properties": { "Name": "Point 4" }, "geometry": { "type": "Point", "coordinates": [ -87.7751496, 41.8946877, 0.0 ] } }
]
}
